gbox_sdk/__init__.py
gbox_sdk/_base_client.py
gbox_sdk/_client.py
gbox_sdk/_compat.py
gbox_sdk/_constants.py
gbox_sdk/_exceptions.py
gbox_sdk/_files.py
gbox_sdk/_models.py
gbox_sdk/_qs.py
gbox_sdk/_resource.py
gbox_sdk/_response.py
gbox_sdk/_streaming.py
gbox_sdk/_types.py
gbox_sdk/_version.py
gbox_sdk/py.typed
gbox_sdk/utils.py
gbox_sdk/_utils/__init__.py
gbox_sdk/_utils/_compat.py
gbox_sdk/_utils/_datetime_parse.py
gbox_sdk/_utils/_logs.py
gbox_sdk/_utils/_proxy.py
gbox_sdk/_utils/_reflection.py
gbox_sdk/_utils/_resources_proxy.py
gbox_sdk/_utils/_streams.py
gbox_sdk/_utils/_sync.py
gbox_sdk/_utils/_transform.py
gbox_sdk/_utils/_typing.py
gbox_sdk/_utils/_utils.py
gbox_sdk/lib/.keep
gbox_sdk/resources/__init__.py
gbox_sdk/resources/v1/__init__.py
gbox_sdk/resources/v1/devices.py
gbox_sdk/resources/v1/v1.py
gbox_sdk/resources/v1/boxes/__init__.py
gbox_sdk/resources/v1/boxes/actions.py
gbox_sdk/resources/v1/boxes/android.py
gbox_sdk/resources/v1/boxes/boxes.py
gbox_sdk/resources/v1/boxes/browser.py
gbox_sdk/resources/v1/boxes/fs.py
gbox_sdk/resources/v1/boxes/media.py
gbox_sdk/resources/v1/boxes/proxy.py
gbox_sdk/resources/v1/boxes/storage.py
gbox_sdk/types/__init__.py
gbox_sdk/types/v1/__init__.py
gbox_sdk/types/v1/android_box.py
gbox_sdk/types/v1/box_create_android_params.py
gbox_sdk/types/v1/box_create_linux_params.py
gbox_sdk/types/v1/box_display_response.py
gbox_sdk/types/v1/box_execute_commands_params.py
gbox_sdk/types/v1/box_execute_commands_response.py
gbox_sdk/types/v1/box_list_params.py
gbox_sdk/types/v1/box_list_response.py
gbox_sdk/types/v1/box_live_view_url_params.py
gbox_sdk/types/v1/box_live_view_url_response.py
gbox_sdk/types/v1/box_resolution_set_params.py
gbox_sdk/types/v1/box_resolution_set_response.py
gbox_sdk/types/v1/box_retrieve_response.py
gbox_sdk/types/v1/box_run_code_params.py
gbox_sdk/types/v1/box_run_code_response.py
gbox_sdk/types/v1/box_start_params.py
gbox_sdk/types/v1/box_start_response.py
gbox_sdk/types/v1/box_stop_params.py
gbox_sdk-0.1.0a41.dist-info/METADATA
gbox_sdk-0.1.0a41.dist-info/WHEEL
gbox_sdk-0.1.0a41.dist-info/licenses/LICENSE
gbox_sdk-0.1.0a41.dist-info/RECORD
