Metadata-Version: 2.3
Name: gbox_sdk
Version: 0.1.0a41
Summary: The official Python library for the gbox-client API
Project-URL: Homepage, https://github.com/babelcloud/gbox-sdk-py
Project-URL: Repository, https://github.com/babelcloud/gbox-sdk-py
Author: Gbox Client
License: Apache-2.0
Classifier: Intended Audience :: Developers
Classifier: License :: OSI Approved :: Apache Software License
Classifier: Operating System :: MacOS
Classifier: Operating System :: Microsoft :: Windows
Classifier: Operating System :: OS Independent
Classifier: Operating System :: POSIX
Classifier: Operating System :: POSIX :: Linux
Classifier: Programming Language :: Python :: 3.8
Classifier: Programming Language :: Python :: 3.9
Classifier: Programming Language :: Python :: 3.10
Classifier: Programming Language :: Python :: 3.11
Classifier: Programming Language :: Python :: 3.12
Classifier: Programming Language :: Python :: 3.13
Classifier: Topic :: Software Development :: Libraries :: Python Modules
Classifier: Typing :: Typed
Requires-Python: >=3.8
Requires-Dist: anyio<5,>=3.5.0
Requires-Dist: distro<2,>=1.7.0
Requires-Dist: httpx<1,>=0.23.0
Requires-Dist: pydantic<3,>=1.9.0
Requires-Dist: sniffio
Requires-Dist: tomli<3,>=2.0.0; python_version < '3.11'
Requires-Dist: typing-extensions<5,>=4.10
Requires-Dist: websocket-client<2,>=1.0.0
Provides-Extra: aiohttp
Requires-Dist: aiohttp; extra == 'aiohttp'
Requires-Dist: httpx-aiohttp>=0.1.8; extra == 'aiohttp'
Provides-Extra: websocket-client
Requires-Dist: websocket-client<2,>=1.0.0; extra == 'websocket-client'
